MAC/rtl/mac.v
module mac(
    input clk,
    input rst,
    input signed [7:0] A,
    input signed [7:0] B,
    output reg signed [15:0] accumulator
);

always @(posedge clk)
begin
    if(rst)
        accumulator <= 16'sd0;
    else
        accumulator <= accumulator + (A * B);
end

endmodule

MAC/tb/mac_verify_tb.v
`timescale 1ns/1ps

module mac_verify_tb;

reg clk;
reg rst;

reg signed [7:0] A;
reg signed [7:0] B;

wire signed [15:0] accumulator;

// Golden reference model
reg signed [15:0] expected;

integer i;

// DUT
mac DUT(
    clk,
    rst,
    A,
    B,
    accumulator
);

// Clock generation
always
begin
    #5 clk = ~clk;
end

initial
begin

    $dumpfile("mac_verify_tb.vcd");
    $dumpvars(0, mac_verify_tb);

    clk = 0;
    rst = 1;
    A = 0;
    B = 0;
    expected = 0;

    // Reset
    #10;
    rst = 0;

    // ---------- Directed Tests ----------

    A = 8'sd2;
    B = 8'sd3;
    expected = expected + (A * B);
    #10;

    if(accumulator == expected)
        $display("PASS : %0d", accumulator);
    else
        $display("FAIL : Expected=%0d Actual=%0d", expected, accumulator);

    A = -8'sd2;
    B = 8'sd4;
    expected = expected + (A * B);
    #10;

    if(accumulator == expected)
        $display("PASS : %0d", accumulator);
    else
        $display("FAIL : Expected=%0d Actual=%0d", expected, accumulator);

    A = -8'sd3;
    B = -8'sd5;
    expected = expected + (A * B);
    #10;

    if(accumulator == expected)
        $display("PASS : %0d", accumulator);
    else
        $display("FAIL : Expected=%0d Actual=%0d", expected, accumulator);

    // ---------- Corner Cases ----------

    A = 0;
    B = 0;
    expected = expected + (A * B);
    #10;

    if(accumulator == expected)
        $display("PASS : Zero Test");
    else
        $display("FAIL : Zero Test");

    A = 8'sd127;
    B = 8'sd1;
    expected = expected + (A * B);
    #10;

    if(accumulator == expected)
        $display("PASS : Max Positive");
    else
        $display("FAIL : Max Positive");

    // ---------- Random Tests ----------

    for(i = 0; i < 20; i = i + 1)
    begin

        A = $random;
        B = $random;

        expected = expected + (A * B);

        #10;

        if(accumulator == expected)
            $display("PASS");
        else
            $display("FAIL : Expected=%0d Actual=%0d",
                     expected,
                     accumulator);

    end

    $display("--------------------------------");
    $display("Verification Complete");
    $display("--------------------------------");

    $finish;

end

endmodule

MAC/mac_verify_tb.vcd
$date
	Sun Jul 12 18:09:28 2026
$end
$version
	Icarus Verilog
$end
$timescale
	1ps
$end
$scope module mac_verify_tb $end
$var wire 16 ! accumulator [15:0] $end
$var reg 8 " A [7:0] $end
$var reg 8 # B [7:0] $end
$var reg 1 $ clk $end
$var reg 16 % expected [15:0] $end
$var reg 1 & rst $end
$var integer 32 ' i [31:0] $end
$scope module DUT $end
$var wire 8 ( A [7:0] $end
$var wire 8 ) B [7:0] $end
$var wire 1 $ clk $end
$var wire 1 & rst $end
$var reg 16 * accumulator [15:0] $end
$upscope $end
$upscope $end
$enddefinitions $end
$comment Show the parameter values. $end
$dumpall
$end
#0
$dumpvars
bx *
b0 )
b0 (
bx '
1&
b0 %
0$
b0 #
b0 "
bx !
$end
#5000
b0 !
b0 *
1$
#10000
0$
b110 %
b11 #
b11 )
b10 "
b10 (
0&
#15000
b110 !
b110 *
1$
#20000
0$
b1111111111111110 %
b100 #
b100 )
b11111110 "
b11111110 (
#25000
b1111111111111110 !
b1111111111111110 *
1$
#30000
0$
b1101 %
b11111011 #
b11111011 )
b11111101 "
b11111101 (
#35000
b1101 !
b1101 *
1$
#40000
0$
b0 #
b0 )
b0 "
b0 (
#45000
1$
#50000
0$
b10001100 %
b1 #
b1 )
b1111111 "
b1111111 (
#55000
b10001100 !
b10001100 *
1$
#60000
0$
b1110111010110000 %
b10000001 #
b10000001 )
b100100 "
b100100 (
b0 '
#65000
b1110111010110000 !
b1110111010110000 *
1$
#70000
0$
b1111001000101011 %
b1100011 #
b1100011 )
b1001 "
b1001 (
b1 '
#75000
b1111001000101011 !
b1111001000101011 *
1$
#80000
0$
b1110110001010100 %
b10001101 #
b10001101 )
b1101 "
b1101 (
b10 '
#85000
b1110110001010100 !
b1110110001010100 *
1$
#90000
0$
b1111001101101110 %
b10010 #
b10010 )
b1100101 "
b1100101 (
b11 '
#95000
b1111001101101110 !
b1111001101101110 *
1$
#100000
0$
b1111001101111011 %
b1101 #
b1101 )
b1 "
b1 (
b100 '
#105000
b1111001101111011 !
b1111001101111011 *
1$
#110000
0$
b111110011001 %
b111101 #
b111101 )
b1110110 "
b1110110 (
b101 '
#115000
b111110011001 !
b111110011001 *
1$
#120000
0$
b1100000110101 %
b10001100 #
b10001100 )
b11101101 "
b11101101 (
b110 '
#125000
b1100000110101 !
b1100000110101 *
1$
#130000
0$
b1100111001011 %
b11000110 #
b11000110 )
b11111001 "
b11111001 (
b111 '
#135000
b1100111001011 !
b1100111001011 *
1$
#140000
0$
b10110110011101 %
b10101010 #
b10101010 )
b11000101 "
b11000101 (
b1000 '
#145000
b10110110011101 !
b10110110011101 *
1$
#150000
0$
b10000100010000 %
b1110111 #
b1110111 )
b11100101 "
b11100101 (
b1001 '
#155000
b10000100010000 !
b10000100010000 *
1$
#160000
0$
b1100100011110 %
b10001111 #
b10001111 )
b10010 "
b10010 (
b1010 '
#165000
b1100100011110 !
b1100100011110 *
1$
#170000
0$
b1101111011010 %
b11001110 #
b11001110 )
b11110010 "
b11110010 (
b1011 '
#175000
b1101111011010 !
b1101111011010 *
1$
#180000
0$
b10000101100010 %
b11000101 #
b11000101 )
b11101000 "
b11101000 (
b1100 '
#185000
b10000101100010 !
b10000101100010 *
1$
#190000
0$
b100101001110 %
b10111101 #
b10111101 )
b1011100 "
b1011100 (
b1101 '
#195000
b100101001110 !
b100101001110 *
1$
#200000
0$
b1101100001111 %
b1100101 #
b1100101 )
b101101 "
b101101 (
b1110 '
#205000
b1101100001111 !
b1101100001111 *
1$
#210000
0$
b1111011101101 %
b1010 #
b1010 )
b1100011 "
b1100011 (
b1111 '
#215000
b1111011101101 !
b1111011101101 *
1$
#220000
0$
b111011101101 %
b100000 #
b100000 )
b10000000 "
b10000000 (
b10000 '
#225000
b111011101101 !
b111011101101 *
1$
#230000
0$
b11000000101111 %
b10011101 #
b10011101 )
b10101010 "
b10101010 (
b10001 '
#235000
b11000000101111 !
b11000000101111 *
1$
#240000
0$
b10100001010001 %
b10011 #
b10011 )
b10010110 "
b10010110 (
b10010 '
#245000
b10100001010001 !
b10100001010001 *
1$
#250000
0$
b10110010001000 %
b1010011 #
b1010011 )
b1101 "
b1101 (
b10011 '
#255000
b10110010001000 !
b10110010001000 *
1$
#260000
0$
b10100 '
