MAC/rtl/mac_parameterized.v
module mac_parameterized
#(
    parameter WIDTH = 8
)
(
    input clk,
    input rst,

    input signed [WIDTH-1:0] A,
    input signed [WIDTH-1:0] B,

    output reg signed [(2*WIDTH)-1:0] accumulator
);

always @(posedge clk)
begin
    if(rst)
        accumulator <= 0;
    else
        accumulator <= accumulator + (A * B);
end

endmodule

MAC/tb/mac_parameterized_tb.v


module mac_parameterized_tb;

parameter WIDTH = 8;

reg clk;
reg rst;

reg signed [WIDTH-1:0] A;
reg signed [WIDTH-1:0] B;

wire signed [(2*WIDTH)-1:0] accumulator;

reg signed [(2*WIDTH)-1:0] expected;

integer i;

// DUT
mac_parameterized
#(
    .WIDTH(WIDTH)
)
DUT
(
    .clk(clk),
    .rst(rst),
    .A(A),
    .B(B),
    .accumulator(accumulator)
);

// Clock Generation
always
begin
    #5 clk = ~clk;
end

initial
begin

    $dumpfile("mac_parameterized_tb.vcd");
    $dumpvars(0, mac_parameterized_tb);

    clk = 0;
    rst = 1;
    A = 0;
    B = 0;
    expected = 0;

    // Reset
    #10;
    rst = 0;

    // -------------------------
    // Directed Tests
    // -------------------------

    A = 2;
    B = 3;
    expected = expected + (A * B);
    #10;

    if(accumulator == expected)
        $display("PASS : %0d", accumulator);
    else
        $display("FAIL : Expected=%0d Actual=%0d", expected, accumulator);

    A = -2;
    B = 4;
    expected = expected + (A * B);
    #10;

    if(accumulator == expected)
        $display("PASS : %0d", accumulator);
    else
        $display("FAIL : Expected=%0d Actual=%0d", expected, accumulator);

    A = -3;
    B = -5;
    expected = expected + (A * B);
    #10;

    if(accumulator == expected)
        $display("PASS : %0d", accumulator);
    else
        $display("FAIL : Expected=%0d Actual=%0d", expected, accumulator);

    // -------------------------
    // Corner Cases
    // -------------------------

    A = 0;
    B = 0;
    expected = expected + (A * B);
    #10;

    if(accumulator == expected)
        $display("PASS : Zero Test");
    else
        $display("FAIL : Zero Test");

    A = 127;
    B = 1;
    expected = expected + (A * B);
    #10;

    if(accumulator == expected)
        $display("PASS : Max Positive");
    else
        $display("FAIL : Max Positive");

    A = -128;
    B = 1;
    expected = expected + (A * B);
    #10;

    if(accumulator == expected)
        $display("PASS : Max Negative");
    else
        $display("FAIL : Max Negative");

    // -------------------------
    // Random Tests
    // -------------------------

    for(i = 0; i < 20; i = i + 1)
    begin

        A = $random;
        B = $random;

        expected = expected + (A * B);

        #10;

        if(accumulator == expected)
            $display("PASS");
        else
            $display("FAIL : Expected=%0d Actual=%0d",
                     expected,
                     accumulator);

    end

    $display("--------------------------------");
    $display("Parameterized MAC Verification Complete");
    $display("--------------------------------");

    $finish;

end

endmodule

MAC/mac_parameterized_tb.vcd
$date
	Mon Jul 13 10:51:47 2026
$end
$version
	Icarus Verilog
$end
$timescale
	1s
$end
$scope module mac_parameterized_tb $end
$var wire 16 ! accumulator [15:0] $end
$var parameter 32 " WIDTH $end
$var reg 8 # A [7:0] $end
$var reg 8 $ B [7:0] $end
$var reg 1 % clk $end
$var reg 16 & expected [15:0] $end
$var reg 1 ' rst $end
$var integer 32 ( i [31:0] $end
$scope module DUT $end
$var wire 8 ) A [7:0] $end
$var wire 8 * B [7:0] $end
$var wire 1 % clk $end
$var wire 1 ' rst $end
$var parameter 32 + WIDTH $end
$var reg 16 , accumulator [15:0] $end
$upscope $end
$upscope $end
$enddefinitions $end
$comment Show the parameter values. $end
$dumpall
b1000 +
b1000 "
$end
#0
$dumpvars
bx ,
b0 *
b0 )
bx (
1'
b0 &
0%
b0 $
b0 #
bx !
$end
#5
b0 !
b0 ,
1%
#10
0%
b110 &
b11 $
b11 *
b10 #
b10 )
0'
#15
b110 !
b110 ,
1%
#20
0%
b1111111111111110 &
b100 $
b100 *
b11111110 #
b11111110 )
#25
b1111111111111110 !
b1111111111111110 ,
1%
#30
0%
b1101 &
b11111011 $
b11111011 *
b11111101 #
b11111101 )
#35
b1101 !
b1101 ,
1%
#40
0%
b0 $
b0 *
b0 #
b0 )
#45
1%
#50
0%
b10001100 &
b1 $
b1 *
b1111111 #
b1111111 )
#55
b10001100 !
b10001100 ,
1%
#60
0%
b1100 &
b10000000 #
b10000000 )
#65
b1100 !
b1100 ,
1%
#70
0%
b1110111000110000 &
b10000001 $
b10000001 *
b100100 #
b100100 )
b0 (
#75
b1110111000110000 !
b1110111000110000 ,
1%
#80
0%
b1111000110101011 &
b1100011 $
b1100011 *
b1001 #
b1001 )
b1 (
#85
b1111000110101011 !
b1111000110101011 ,
1%
#90
0%
b1110101111010100 &
b10001101 $
b10001101 *
b1101 #
b1101 )
b10 (
#95
b1110101111010100 !
b1110101111010100 ,
1%
#100
0%
b1111001011101110 &
b10010 $
b10010 *
b1100101 #
b1100101 )
b11 (
#105
b1111001011101110 !
b1111001011101110 ,
1%
#110
0%
b1111001011111011 &
b1101 $
b1101 *
b1 #
b1 )
b100 (
#115
b1111001011111011 !
b1111001011111011 ,
1%
#120
0%
b111100011001 &
b111101 $
b111101 *
b1110110 #
b1110110 )
b101 (
#125
b111100011001 !
b111100011001 ,
1%
#130
0%
b1011110110101 &
b10001100 $
b10001100 *
b11101101 #
b11101101 )
b110 (
#135
b1011110110101 !
b1011110110101 ,
1%
#140
0%
b1100101001011 &
b11000110 $
b11000110 *
b11111001 #
b11111001 )
b111 (
#145
b1100101001011 !
b1100101001011 ,
1%
#150
0%
b10110100011101 &
b10101010 $
b10101010 *
b11000101 #
b11000101 )
b1000 (
#155
b10110100011101 !
b10110100011101 ,
1%
#160
0%
b10000010010000 &
b1110111 $
b1110111 *
b11100101 #
b11100101 )
b1001 (
#165
b10000010010000 !
b10000010010000 ,
1%
#170
0%
b1100010011110 &
b10001111 $
b10001111 *
b10010 #
b10010 )
b1010 (
#175
b1100010011110 !
b1100010011110 ,
1%
#180
0%
b1101101011010 &
b11001110 $
b11001110 *
b11110010 #
b11110010 )
b1011 (
#185
b1101101011010 !
b1101101011010 ,
1%
#190
0%
b10000011100010 &
b11000101 $
b11000101 *
b11101000 #
b11101000 )
b1100 (
#195
b10000011100010 !
b10000011100010 ,
1%
#200
0%
b100011001110 &
b10111101 $
b10111101 *
b1011100 #
b1011100 )
b1101 (
#205
b100011001110 !
b100011001110 ,
1%
#210
0%
b1101010001111 &
b1100101 $
b1100101 *
b101101 #
b101101 )
b1110 (
#215
b1101010001111 !
b1101010001111 ,
1%
#220
0%
b1111001101101 &
b1010 $
b1010 *
b1100011 #
b1100011 )
b1111 (
#225
b1111001101101 !
b1111001101101 ,
1%
#230
0%
b111001101101 &
b100000 $
b100000 *
b10000000 #
b10000000 )
b10000 (
#235
b111001101101 !
b111001101101 ,
1%
#240
0%
b10111110101111 &
b10011101 $
b10011101 *
b10101010 #
b10101010 )
b10001 (
#245
b10111110101111 !
b10111110101111 ,
1%
#250
0%
b10011111010001 &
b10011 $
b10011 *
b10010110 #
b10010110 )
b10010 (
#255
b10011111010001 !
b10011111010001 ,
1%
#260
0%
b10110000001000 &
b1010011 $
b1010011 *
b1101 #
b1101 )
b10011 (
#265
b10110000001000 !
b10110000001000 ,
1%
#270
0%
b10100 (
