MAC/rtl/mac_pipeline.v
module mac_pipeline(
    clk,
    rst,
    A,
    B,
    accumulator
);

input clk;
input rst;

input signed [7:0] A;
input signed [7:0] B;

output reg signed [15:0] accumulator;

reg signed [15:0] product_reg;

always @(posedge clk)
begin

    if(rst)
    begin
        product_reg <= 16'sd0;
        accumulator <= 16'sd0;
    end

    else
    begin
        product_reg <= A * B;
        accumulator <= accumulator + product_reg;
    end

end

endmodule

MAC/tb/mac_pipeline_tb.v
`timescale 1ns/1ps

module mac_pipeline_tb;

reg clk;
reg rst;

reg signed [7:0] A;
reg signed [7:0] B;

wire signed [15:0] accumulator;

mac_pipeline DUT(
    clk,
    rst,
    A,
    B,
    accumulator
);

always
begin
    #5 clk = ~clk;
end

initial
begin

    clk = 0;
    rst = 1;
    A = 0;
    B = 0;

    #10;
    rst = 0;

    A = 8'sd2;
    B = 8'sd3;
    #10;

    A = 8'sd4;
    B = 8'sd5;
    #10;

    A = -8'sd2;
    B = 8'sd6;
    #10;

    A = 8'sd3;
    B = -8'sd4;
    #10;

    A = -8'sd2;
    B = -8'sd3;
    #10;

    $finish;

end

initial
begin

    $dumpfile("mac_pipeline_tb.vcd");
    $dumpvars(0, mac_pipeline_tb);

    $monitor(
        "Time=%0t  A=%0d  B=%0d  ProductReg=%0d  Acc=%0d",
        $time,
        A,
        B,
        DUT.product_reg,
        accumulator
    );

end

endmodule

MAC/mac_pipeline_tb.vcd
$date
	Sun Jul 12 17:39:10 2026
$end
$version
	Icarus Verilog
$end
$timescale
	1ps
$end
$scope module mac_pipeline_tb $end
$var wire 16 ! accumulator [15:0] $end
$var reg 8 " A [7:0] $end
$var reg 8 # B [7:0] $end
$var reg 1 $ clk $end
$var reg 1 % rst $end
$scope module DUT $end
$var wire 8 & A [7:0] $end
$var wire 8 ' B [7:0] $end
$var wire 1 $ clk $end
$var wire 1 % rst $end
$var reg 16 ( accumulator [15:0] $end
$var reg 16 ) product_reg [15:0] $end
$upscope $end
$upscope $end
$enddefinitions $end
$comment Show the parameter values. $end
$dumpall
$end
#0
$dumpvars
bx )
bx (
b0 '
b0 &
1%
0$
b0 #
b0 "
bx !
$end
#5000
b0 !
b0 (
b0 )
1$
#10000
0$
b11 #
b11 '
b10 "
b10 &
0%
#15000
b110 )
1$
#20000
0$
b101 #
b101 '
b100 "
b100 &
#25000
b110 !
b110 (
b10100 )
1$
#30000
0$
b110 #
b110 '
b11111110 "
b11111110 &
#35000
b11010 !
b11010 (
b1111111111110100 )
1$
#40000
0$
b11111100 #
b11111100 '
b11 "
b11 &
#45000
b1110 !
b1110 (
1$
#50000
0$
b11111101 #
b11111101 '
b11111110 "
b11111110 &
#55000
b10 !
b10 (
b110 )
1$
