fsm/rtl/fsm_toggle.v
module fsm_toggle(
    input clk,
    input reset,
    input x,
    output reg y
);

reg state;

parameter S0 = 1'b0;
parameter S1 = 1'b1;

always @(posedge clk)
begin
    if (reset)
        state <= S0;
    else
        state <= next_state;
end

reg next_state;

always @(*)
begin
    case(state)

        S0:
            if(x)
                next_state = S1;
            else
                next_state = S0;

        S1:
            if(x)
                next_state = S1;
            else
                next_state = S0;

    endcase
end

always @(*)
begin
    case(state)

        S0: y = 0;
        S1: y = 1;

    endcase
end

endmodule

fsm/tb/fsm_toggle_tb.v
module fsm_toggle_tb;

reg clk;
reg reset;
reg x;
wire y;

fsm_toggle dut(
    .clk(clk),
    .reset(reset),
    .x(x),
    .y(y)
);

initial begin
    $dumpfile("fsm_toggle_tb.vcd");
    $dumpvars(0, fsm_toggle_tb);

    clk = 0;
    forever #5 clk = ~clk;
end

initial begin
    reset = 1;
    x = 0;
    #10;

    reset = 0;
    x = 0;
    #10;

    x = 1;
    #10;

    x = 1;
    #10;

    x = 0;
    #10;

    x = 1;
    #10;

    x = 0;
    #10;

    $finish;
end

endmodule

fsm/fsm_toggle_tb.vcd
$date
	Sat Jul 04 12:11:13 2026
$end
$version
	Icarus Verilog
$end
$timescale
	1s
$end
$scope module fsm_toggle_tb $end
$var wire 1 ! y $end
$var reg 1 " clk $end
$var reg 1 # reset $end
$var reg 1 $ x $end
$scope module dut $end
$var wire 1 " clk $end
$var wire 1 # reset $end
$var wire 1 $ x $end
$var parameter 1 % S0 $end
$var parameter 1 & S1 $end
$var reg 1 ' next_state $end
$var reg 1 ( state $end
$var reg 1 ! y $end
$upscope $end
$upscope $end
$enddefinitions $end
$comment Show the parameter values. $end
$dumpall
1&
0%
$end
#0
$dumpvars
x(
x'
0$
1#
0"
x!
$end
#5
0!
0'
0(
1"
#10
0"
0#
#15
1"
#20
1'
0"
1$
#25
1!
1(
1"
#30
0"
#35
1"
#40
0'
0"
0$
#45
0!
0(
1"
#50
1'
0"
1$
#55
1!
1(
1"
#60
0'
0"
0$
#65
0!
0(
1"
