fsm/rtl/traffic_light.v
module traffic_light(
    input clk,
    input reset,
    output reg red,
    output reg yellow,
    output reg green
);

parameter RED = 2'b00;
parameter GREEN = 2'b01;
parameter YELLOW = 2'b10;

reg [1:0] state, next_state;
reg timer;

always @(posedge clk)
begin
    if (reset)
        state <= RED;
    else
        state <= next_state;
end

always @(posedge clk)
begin
    if (reset)
        timer <= 0;
    else
        timer <= ~timer;
end

always @(*)
begin
    case(state)

        RED:
            if (timer)
                next_state = GREEN;
            else
                next_state = RED;

        GREEN:
            if (timer)
                next_state = YELLOW;
            else
                next_state = GREEN;

        YELLOW:
            if (timer)
                next_state = RED;
            else
                next_state = YELLOW;

        default:
            next_state = RED;

    endcase
end

always @(*)
begin
    red = 0;
    yellow = 0;
    green = 0;

    case(state)

        RED:
            red = 1;

        GREEN:
            green = 1;

        YELLOW:
            yellow = 1;

    endcase
end

endmodule

fsm/tb/traffic_light_tb.v
`timescale 1ns/1ps

module traffic_light_tb;

reg clk;
reg reset;

wire red;
wire yellow;
wire green;

traffic_light dut(
    .clk(clk),
    .reset(reset),
    .red(red),
    .yellow(yellow),
    .green(green)
);

initial begin
    $dumpfile("traffic_light_tb.vcd");
    $dumpvars(0, traffic_light_tb);
end

initial begin
    clk = 0;
    forever #5 clk = ~clk;
end

initial begin
    reset = 1;

    #10;
    reset = 0;

    #100;

    $finish;
end

initial begin
    $monitor(
        "Time=%0t Reset=%b Red=%b Yellow=%b Green=%b",
        $time,
        reset,
        red,
        yellow,
        green
    );
end

endmodule

fsm/traffic_light_tb.vcd
$date
	Sat Jul 04 12:48:17 2026
$end
$version
	Icarus Verilog
$end
$timescale
	1ps
$end
$scope module traffic_light_tb $end
$var wire 1 ! yellow $end
$var wire 1 " red $end
$var wire 1 # green $end
$var reg 1 $ clk $end
$var reg 1 % reset $end
$scope module dut $end
$var wire 1 $ clk $end
$var wire 1 % reset $end
$var parameter 2 & GREEN $end
$var parameter 2 ' RED $end
$var parameter 2 ( YELLOW $end
$var reg 1 # green $end
$var reg 2 ) next_state [1:0] $end
$var reg 1 " red $end
$var reg 2 * state [1:0] $end
$var reg 1 + timer $end
$var reg 1 ! yellow $end
$upscope $end
$upscope $end
$enddefinitions $end
$comment Show the parameter values. $end
$dumpall
b10 (
b0 '
b1 &
$end
#0
$dumpvars
x+
bx *
bx )
1%
0$
x#
x"
x!
$end
#5000
0#
0!
1"
b0 )
b0 *
0+
1$
#10000
0$
0%
#15000
b1 )
1+
1$
#20000
0$
#25000
1#
0"
b1 *
0+
1$
#30000
0$
#35000
b10 )
1+
1$
#40000
0$
#45000
1!
0#
b10 *
0+
1$
#50000
0$
#55000
b0 )
1+
1$
#60000
0$
#65000
1"
0!
b0 *
0+
1$
#70000
0$
#75000
b1 )
1+
1$
#80000
0$
#85000
1#
0"
b1 *
0+
1$
#90000
0$
#95000
b10 )
1+
1$
#100000
0$
#105000
1!
0#
b10 *
0+
1$
