fsm/rtl/vending_machine.v
module vending_machine(
    input clk,
    input reset,
    input coin5,
    input coin10,
    output reg dispense
);

parameter S0  = 2'b00;
parameter S5  = 2'b01;
parameter S10 = 2'b10;

reg [1:0] state, next_state;

always @(posedge clk)
begin
    if(reset)
        state <= S0;
    else
        state <= next_state;
end

always @(*)
begin
    case(state)

        S0:
            if(coin10)
                next_state = S10;
            else if(coin5)
                next_state = S5;
            else
                next_state = S0;

        S5:
            if(coin5 || coin10)
                next_state = S10;
            else
                next_state = S5;

        S10:
            next_state = S0;

        default:
            next_state = S0;

    endcase
end

always @(*)
begin
    case(state)

        S0:
            dispense = 0;

        S5:
            dispense = 0;

        S10:
            dispense = 1;

        default:
            dispense = 0;

    endcase
end

endmodule

fsm/tb/vending_machine_tb.v
module vending_machine_tb;

reg clk;
reg reset;
reg coin5;
reg coin10;

wire dispense;

vending_machine dut(
    .clk(clk),
    .reset(reset),
    .coin5(coin5),
    .coin10(coin10),
    .dispense(dispense)
);

initial begin
    $dumpfile("vending_machine_tb.vcd");
    $dumpvars(0,vending_machine_tb);
end

initial begin
    clk = 0;
    forever #5 clk = ~clk;
end

initial begin

    reset = 1;
    coin5 = 0;
    coin10 = 0;

    #10;
    reset = 0;

    // Insert ₹5
    #10;
    coin5 = 1;
    #10;
    coin5 = 0;

    // Insert another ₹5
    #10;
    coin5 = 1;
    #10;
    coin5 = 0;

    // Insert ₹10 directly
    #20;
    coin10 = 1;
    #10;
    coin10 = 0;

    #20;

    $finish;

end

initial begin
    $monitor(
        "Time=%0t coin5=%b coin10=%b dispense=%b",
        $time,
        coin5,
        coin10,
        dispense
    );
end

endmodule

fsm/vending_machine_tb.vcd
$date
	Sat Jul 04 13:21:38 2026
$end
$version
	Icarus Verilog
$end
$timescale
	1s
$end
$scope module vending_machine_tb $end
$var wire 1 ! dispense $end
$var reg 1 " clk $end
$var reg 1 # coin10 $end
$var reg 1 $ coin5 $end
$var reg 1 % reset $end
$scope module dut $end
$var wire 1 " clk $end
$var wire 1 # coin10 $end
$var wire 1 $ coin5 $end
$var wire 1 % reset $end
$var parameter 2 & S0 $end
$var parameter 2 ' S10 $end
$var parameter 2 ( S5 $end
$var reg 1 ! dispense $end
$var reg 2 ) next_state [1:0] $end
$var reg 2 * state [1:0] $end
$upscope $end
$upscope $end
$enddefinitions $end
$comment Show the parameter values. $end
$dumpall
b1 (
b10 '
b0 &
$end
#0
$dumpvars
bx *
b0 )
1%
0$
0#
0"
x!
$end
#5
0!
b0 *
1"
#10
0"
0%
#15
1"
#20
b1 )
0"
1$
#25
b10 )
b1 *
1"
#30
b1 )
0"
0$
#35
1"
#40
b10 )
0"
1$
#45
1!
b0 )
b10 *
1"
#50
0"
0$
#55
0!
b0 *
1"
#60
0"
#65
1"
#70
b10 )
0"
1#
#75
1!
b0 )
b10 *
1"
#80
0"
0#
#85
0!
b0 *
1"
