ALU/rtl/alu8.v
module alu8(
    A,
    B,
    opcode,
    result,
    carry,
    zero
);

input [7:0] A;
input [7:0] B;
input [2:0] opcode;

output reg [7:0] result;
output reg carry;
output reg zero;

reg [8:0] temp;

always @(*)
begin

    carry = 0;

    case(opcode)

        3'b000:
        begin
            temp = A + B;
            result = temp[7:0];
            carry = temp[8];
        end

        3'b001:
        begin
            temp = A - B;
            result = temp[7:0];
            carry = temp[8];
        end

        3'b010:
        begin
            result = A & B;
        end

        3'b011:
        begin
            result = A | B;
        end

        3'b100:
        begin
            result = A ^ B;
        end

        3'b101:
        begin
            result = ~A;
        end

        3'b110:
        begin
            result = A << 1;
        end

        3'b111:
        begin
            result = A >> 1;
        end

        default:
        begin
            result = 8'b00000000;
        end

    endcase

    if(result == 8'b00000000)
        zero = 1;
    else
        zero = 0;

end

endmodule

ALU/tb/alu8_tb.v
module alu8_tb;

reg [7:0] A;
reg [7:0] B;
reg [2:0] opcode;

wire [7:0] result;
wire carry;
wire zero;

alu8 DUT(
    A,
    B,
    opcode,
    result,
    carry,
    zero
);

initial
begin

    $dumpfile("alu8_tb.vcd");
    $dumpvars(0, alu8_tb);

    A = 8'd15;
    B = 8'd10;
    opcode = 3'b000;
    #10;

    A = 8'd15;
    B = 8'd5;
    opcode = 3'b001;
    #10;

    A = 8'b11001100;
    B = 8'b10101010;
    opcode = 3'b010;
    #10;

    A = 8'b11001100;
    B = 8'b10101010;
    opcode = 3'b011;
    #10;

    A = 8'b11001100;
    B = 8'b10101010;
    opcode = 3'b100;
    #10;

    A = 8'b11001100;
    B = 8'd0;
    opcode = 3'b101;
    #10;

    A = 8'd25;
    B = 8'd0;
    opcode = 3'b110;
    #10;

    A = 8'd25;
    B = 8'd0;
    opcode = 3'b111;
    #10;

    A = 8'd5;
    B = 8'd5;
    opcode = 3'b001;
    #10;

    $finish;

end

initial
begin

    $monitor(
        "Time=%0t  Opcode=%b  A=%d  B=%d  Result=%d  Carry=%b  Zero=%b",
        $time,
        opcode,
        A,
        B,
        result,
        carry,
        zero
    );

end

endmodule

ALU/alu8_tb.vcd
$date
	Tue Jul 07 18:14:45 2026
$end
$version
	Icarus Verilog
$end
$timescale
	1ps
$end
$scope module alu8_tb $end
$var wire 1 ! zero $end
$var wire 8 " result [7:0] $end
$var wire 1 # carry $end
$var reg 8 $ A [7:0] $end
$var reg 8 % B [7:0] $end
$var reg 3 & opcode [2:0] $end
$scope module DUT $end
$var wire 8 ' A [7:0] $end
$var wire 8 ( B [7:0] $end
$var wire 3 ) opcode [2:0] $end
$var reg 1 # carry $end
$var reg 8 * result [7:0] $end
$var reg 9 + temp [8:0] $end
$var reg 1 ! zero $end
$upscope $end
$upscope $end
$enddefinitions $end
$comment Show the parameter values. $end
$dumpall
$end
#0
$dumpvars
b11001 +
b11001 *
b0 )
b1010 (
b1111 '
b0 &
b1010 %
b1111 $
0#
b11001 "
0!
$end
#10000
b1010 "
b1010 *
b1010 +
b1 &
b1 )
b101 %
b101 (
#20000
b10001000 "
b10001000 *
b10 &
b10 )
b10101010 %
b10101010 (
b11001100 $
b11001100 '
#30000
b11101110 "
b11101110 *
b11 &
b11 )
#40000
b1100110 "
b1100110 *
b100 &
b100 )
#50000
b110011 "
b110011 *
b101 &
b101 )
b0 %
b0 (
#60000
b110010 "
b110010 *
b110 &
b110 )
b11001 $
b11001 '
#70000
b1100 "
b1100 *
b111 &
b111 )
#80000
1!
b0 "
b0 *
b0 +
b1 &
b1 )
b101 %
b101 (
b101 $
b101 '
