week 2/rtl/counter.v
module counter(
    input clk,
    input reset,
    output reg [3:0] count
);

always @(posedge clk)
begin
    if (reset)
        count <= 4'b0000;
    else
        count <= count + 1;
end

endmodule

week 2/tb/counter_tb.v
module counter_tb;

reg clk;
reg reset;
wire [3:0] count;

counter dut(
    .clk(clk),
    .reset(reset),
    .count(count)
);

initial begin
    $dumpfile("counter_tb.vcd");
    $dumpvars(0, counter_tb);

    clk = 0;
    forever #5 clk = ~clk;
end

initial begin
    reset = 1;
    #10;

    reset = 0;
    #50;

    reset = 1;
    #10;

    reset = 0;
    #30;

    $finish;
end

endmodule

week 2/counter_tb.vcd
$date
	Thu Jun 25 09:10:33 2026
$end
$version
	Icarus Verilog
$end
$timescale
	1s
$end
$scope module counter_tb $end
$var wire 4 ! count [3:0] $end
$var reg 1 " clk $end
$var reg 1 # reset $end
$scope module dut $end
$var wire 1 " clk $end
$var wire 1 # reset $end
$var reg 4 $ count [3:0] $end
$upscope $end
$upscope $end
$enddefinitions $end
$comment Show the parameter values. $end
$dumpall
$end
#0
$dumpvars
bx $
1#
0"
bx !
$end
#5
b0 !
b0 $
1"
#10
0"
0#
#15
b1 !
b1 $
1"
#20
0"
#25
b10 !
b10 $
1"
#30
0"
#35
b11 !
b11 $
1"
#40
0"
#45
b100 !
b100 $
1"
#50
0"
#55
b101 !
b101 $
1"
#60
0"
1#
#65
b0 !
b0 $
1"
#70
0"
0#
#75
b1 !
b1 $
1"
#80
0"
#85
b10 !
b10 $
1"
#90
0"
#95
b11 !
b11 $
1"
