week 2/rtl/dff_reset.v
module dff_reset(
    input clk,
    input reset,
    input d,
    output reg q
);

always @(posedge clk)
begin
    if (reset)
        q <= 0;
    else
        q <= d;
end

endmodule

week 2/tb/dff_reset_tb.v
module dff_reset_tb;

reg clk;
reg reset;
reg d;
wire q;

dff_reset dut(
    .clk(clk),
    .reset(reset),
    .d(d),
    .q(q)
);

initial begin
    $dumpfile("dff_reset_tb.vcd");
    $dumpvars(0, dff_reset_tb);

    clk = 0;
    forever #5 clk = ~clk;
end

initial begin
    reset = 1;
    d = 0;
    #10;

    reset = 0;
    d = 1;
    #10;

    d = 0;
    #10;

    d = 1;
    #10;

    reset = 1;
    #10;

    reset = 0;
    d = 0;
    #10;

    $finish;
end

endmodule

week 2/dff_reset_tb.vcd
$date
	Thu Jun 25 08:03:10 2026
$end
$version
	Icarus Verilog
$end
$timescale
	1s
$end
$scope module dff_reset_tb $end
$var wire 1 ! q $end
$var reg 1 " clk $end
$var reg 1 # d $end
$var reg 1 $ reset $end
$scope module dut $end
$var wire 1 " clk $end
$var wire 1 # d $end
$var wire 1 $ reset $end
$var reg 1 ! q $end
$upscope $end
$upscope $end
$enddefinitions $end
$comment Show the parameter values. $end
$dumpall
$end
#0
$dumpvars
1$
0#
0"
x!
$end
#5
0!
1"
#10
0"
1#
0$
#15
1!
1"
#20
0"
0#
#25
0!
1"
#30
0"
1#
#35
1!
1"
#40
0"
1$
#45
0!
1"
#50
0"
0#
0$
