week 2/rtl/dff.v
module dff(
    input clk,
    input d,
    output reg q
);

always @(posedge clk)
begin
    q <= d;
end

endmodule

week 2/tb/dff_tb.v
module dff_tb;
reg clk,d;
wire q;

dff dut(
    .clk(clk),
    .d(d),
    .q(q)
);

initial
begin
    $dumpfile("dff_tb.vcd");
    $dumpvars(0,dff_tb);

    clk = 0;
    forever 
        #5 clk = ~clk;      
    end

    initial begin
        d=0;
        #10 d=1;
        #10 d=0;
        #10 d=1;
        #10
        $finish;
    end
    endmodule

week 2/dff_tb.vcd
$date
	Mon Jul 06 20:36:29 2026
$end
$version
	Icarus Verilog
$end
$timescale
	1s
$end
$scope module dff_tb $end
$var wire 1 ! q $end
$var reg 1 " clk $end
$var reg 1 # d $end
$scope module dut $end
$var wire 1 " clk $end
$var wire 1 # d $end
$var reg 1 ! q $end
$upscope $end
$upscope $end
$enddefinitions $end
$comment Show the parameter values. $end
$dumpall
$end
#0
$dumpvars
0#
0"
x!
$end
#5
0!
1"
#10
0"
1#
#15
1!
1"
#20
0"
0#
#25
0!
1"
#30
0"
1#
#35
1!
1"
