week 2/rtl/register.v
module register(
    input clk,
    input reset,
    input [7:0] d,
    output reg [7:0] q
);

always @(posedge clk)
begin
    if (reset)
        q <= 8'b00000000;
    else
        q <= d;
end

endmodule

week 2/tb/register_tb.v
module register_tb;

reg clk;
reg reset;
reg [7:0] d;
wire [7:0] q;

register dut(
    .clk(clk),
    .reset(reset),
    .d(d),
    .q(q)
);

initial begin
    $dumpfile("register_tb.vcd");
    $dumpvars(0, register_tb);

    clk = 0;
    forever #5 clk = ~clk;
end

initial begin
    reset = 1;
    d = 8'b00000000;
    #10;

    reset = 0;
    d = 8'b10101010;
    #10;

    d = 8'b11110000;
    #10;

    d = 8'b00001111;
    #10;

    reset = 1;
    #10;

    reset = 0;
    d = 8'b11001100;
    #10;

    $finish;
end

endmodule

week 2/register_tb.vcd
$date
	Thu Jun 25 08:17:10 2026
$end
$version
	Icarus Verilog
$end
$timescale
	1s
$end
$scope module register_tb $end
$var wire 8 ! q [7:0] $end
$var reg 1 " clk $end
$var reg 8 # d [7:0] $end
$var reg 1 $ reset $end
$scope module dut $end
$var wire 1 " clk $end
$var wire 8 % d [7:0] $end
$var wire 1 $ reset $end
$var reg 8 & q [7:0] $end
$upscope $end
$upscope $end
$enddefinitions $end
$comment Show the parameter values. $end
$dumpall
$end
#0
$dumpvars
bx &
b0 %
1$
b0 #
0"
bx !
$end
#5
b0 !
b0 &
1"
#10
0"
b10101010 #
b10101010 %
0$
#15
b10101010 !
b10101010 &
1"
#20
0"
b11110000 #
b11110000 %
#25
b11110000 !
b11110000 &
1"
#30
0"
b1111 #
b1111 %
#35
b1111 !
b1111 &
1"
#40
0"
1$
#45
b0 !
b0 &
1"
#50
0"
b11001100 #
b11001100 %
0$
#55
b11001100 !
b11001100 &
1"
